binarystar/__init__.py
binarystar-0.1.0.dist-info/LICENSE
binarystar-0.1.0.dist-info/METADATA
binarystar-0.1.0.dist-info/WHEEL
binarystar-0.1.0.dist-info/top_level.txt
binarystar-0.1.0.dist-info/RECORD
