Metadata-Version: 2.1
Name: binarystar
Version: 0.1.0
Summary: High level machine learning models training package
Home-page: https://github.com/ermenkov/binarystar
Author: Viktor Eremnkov
Author-email: viktor.ermenkov@gmail.com
License: MIT
Platform: UNKNOWN
